[
  {
    "id": 1,
    "name": "COMICS",
    "imageUrl": "https://wallpapercave.com/wp/wp2903360.jpg"
  },
  {
    "id": 2,
    "name": "SERIES",
    "imageUrl": "https://wallpaperplay.com/walls/full/8/2/9/323965.jpg"
  },
  {
    "id": 3,
    "name": "CHARACTERS",
    "imageUrl": "https://d1rbbjrn2xovty.cloudfront.net/MAR14_Previews/26563235816_big.jpg"
  },
  {
    "id": 4,
    "name": "CREATORS",
    "imageUrl": "https://images.newrepublic.com/ba645476820609fec83ad47e61858892aef0fbce.jpeg?w=1200&q=65&dpi=2.625&fm=pjpg&h=497"
  }
]